{"card_name": "Memento Gorgon", "color": "B", "rarity": "common", "type": "Creature \u2013 Gorgon", "number": 107, "color_identity": "B", "cost": "{2}{B}{B}", "rules_text": "When Memento Gorgon enters the battlefield, mill X cards, where X is your devotion to black. Then return a card milled this way to your hand. You lose 1 life. [i](Each {B} in the mana costs of permanents you control counts toward your devotion to black.)[/i]", "pt": "2/4", "special_text": "", "shape": "normal", "set": "TTR", "loyalty": "", "notes": "alt art https://www.deviantart.com/athena-erocith/art/The-Dark-Eye-Memoria-Halef-578717417"}