{"card_name": "Miserable Discovery", "color": "B", "rarity": "common", "type": "Enchantment", "number": 110, "color_identity": "B", "cost": "{B}", "rules_text": "When Miserable Discovery enters the battlefield, you lose 1 life and create a tapped Treasure token. [i](It\u2019s an artifact with \u201c{T}, Sacrifice this artifact: Add one mana of any color.\u201d)[/i]\n{2}{B}, Sacrifice Miserable Discovery: You draw two cards and you lose 2 life.", "pt": "", "special_text": "", "shape": "normal", "set": "TTR", "loyalty": "", "notes": "QCX\nCard draw (for some resource in addition to mana, usually life)"}