{"card_name": "Kederekt Deepdweller", "color": "UB", "rarity": "mythic", "type": "Creature \u2013 Horror", "number": 194, "color_identity": "UB", "cost": "{2}{U}{B}", "rules_text": "Whenever you cast an instant or sorcery spell, Kederekt Deepdweller gains your choice of menace, lifelink, or indestructible until end of turn.\nWhenever Kederekt Deepdweller deals combat damage to a player, you draw a card and that player discards a card.", "pt": "4/4", "special_text": "", "shape": "normal", "set": "ALR", "loyalty": "", "notes": ""}